wdapy/__init__.py
wdapy/_alert.py
wdapy/_base.py
wdapy/_proto.py
wdapy/_types.py
wdapy/_utils.py
wdapy/_wdapy.py
wdapy/_wrap.py
wdapy/actions.py
wdapy/exceptions.py
wdapy/usbmux/__init__.py
wdapy/usbmux/exceptions.py
wdapy/usbmux/pyusbmux.py
wdapy-1.0.0.dist-info/LICENSE
wdapy-1.0.0.dist-info/METADATA
wdapy-1.0.0.dist-info/WHEEL
wdapy-1.0.0.dist-info/pbr.json
wdapy-1.0.0.dist-info/top_level.txt
wdapy-1.0.0.dist-info/RECORD
