Metadata-Version: 2.1
Name: wdapy
Version: 1.0.0
Summary: Python Client for Facebook WebDriverAgent
Home-page: https://github.com/openatx/wdapy
Author: "codeskyblue"
License: MIT
Platform: UNKNOWN
Classifier: Development Status :: 3 - Alpha
Classifier: Environment :: Console
Classifier: Intended Audience :: Developers
Classifier: Operating System :: POSIX :: Linux
Classifier: Programming Language :: Python :: 3.6
Classifier: Programming Language :: Python :: 3.7
Classifier: Programming Language :: Python :: 3.8
Classifier: Programming Language :: Python :: 3.9
Classifier: Topic :: Software Development :: Libraries :: Python Modules
Classifier: Topic :: Software Development :: Testing
Requires-Python: >=3.8
License-File: LICENSE
Requires-Dist: Deprecated>=1.2.6
Requires-Dist: Pillow
Requires-Dist: retry
Requires-Dist: construct>=2
Requires-Dist: pydantic>=2.5.1
